{
  "WebkitGTK::BackForwardList": {
    "mast": 0.009e0,
    "moar": 0e0,
    "optimize": 0.003e0,
    "syntaxcheck": 0.001e0,
    "ast": 0e0,
    "start": 0e0,
    "mbc": 0.001e0,
    "parse": 4.086e0
  },
  "WebkitGTK::Raw::WebView": {
    "parse": 13.25e0,
    "mbc": 0.004e0,
    "start": 0e0,
    "ast": 0e0,
    "syntaxcheck": 0e0,
    "moar": 0e0,
    "optimize": 0.003e0,
    "mast": 0.011e0
  },
  "WebkitGTK::PrintCustomWidget": {
    "mast": 0.009e0,
    "moar": 0e0,
    "optimize": 0.002e0,
    "syntaxcheck": 0e0,
    "start": 0e0,
    "ast": 0e0,
    "parse": 4.749e0,
    "mbc": 0.001e0
  },
  "WebkitGTK::NetworkProxySettings": {
    "start": 0e0,
    "ast": 0e0,
    "parse": 3.934e0,
    "mbc": 0.001e0,
    "mast": 0.01e0,
    "moar": 0e0,
    "optimize": 0.002e0,
    "syntaxcheck": 0e0
  },
  "WebkitGTK::Raw::URIResponse": {
    "optimize": 0.002e0,
    "moar": 0e0,
    "syntaxcheck": 0e0,
    "mast": 0.01e0,
    "mbc": 0.002e0,
    "parse": 4.425e0,
    "ast": 0e0,
    "start": 0e0
  },
  "WebkitGTK::ContextMenuItem": {
    "moar": 0e0,
    "syntaxcheck": 0e0,
    "optimize": 0.002e0,
    "mast": 0.011e0,
    "parse": 4.962e0,
    "mbc": 0.002e0,
    "start": 0e0,
    "ast": 0e0
  },
  "WebkitGTK::BackForwardListItem": {
    "parse": 3.942e0,
    "mbc": 0.002e0,
    "start": 0e0,
    "ast": 0e0,
    "optimize": 0.002e0,
    "moar": 0e0,
    "syntaxcheck": 0e0,
    "mast": 0.01e0
  },
  "WebkitGTK::Roles::Signals::BackForwardList": {
    "optimize": 0.002e0,
    "moar": 0e0,
    "syntaxcheck": 0e0,
    "mast": 0.009e0,
    "mbc": 0.001e0,
    "parse": 4.243e0,
    "ast": 0e0,
    "start": 0e0
  },
  "WebkitGTK::Raw::ConsoleMessage": {
    "moar": 0e0,
    "optimize": 0.003e0,
    "syntaxcheck": 0e0,
    "mast": 0.011e0,
    "parse": 4.506e0,
    "mbc": 0.002e0,
    "start": 0e0,
    "ast": 0e0
  },
  "WebkitGTK::Raw::EditorState": {
    "parse": 4.838e0,
    "mbc": 0.001e0,
    "start": 0e0,
    "ast": 0e0,
    "moar": 0e0,
    "syntaxcheck": 0e0,
    "optimize": 0.002e0,
    "mast": 0.008e0
  },
  "WebkitGTK::JavaScript::Class": {
    "mbc": 0.001e0,
    "parse": 4.325e0,
    "ast": 0e0,
    "start": 0e0,
    "moar": 0e0,
    "syntaxcheck": 0e0,
    "optimize": 0.002e0,
    "mast": 0.01e0
  },
  "WebkitGTK::Raw::SecurityOrigin": {
    "mast": 0.012e0,
    "syntaxcheck": 0e0,
    "moar": 0e0,
    "optimize": 0.003e0,
    "ast": 0e0,
    "start": 0e0,
    "mbc": 0.002e0,
    "parse": 5.121e0
  },
  "WebkitGTK::Roles::Signals::WebContext": {
    "start": 0e0,
    "ast": 0e0,
    "parse": 4.493e0,
    "mbc": 0.002e0,
    "mast": 0.008e0,
    "moar": 0e0,
    "optimize": 0.004e0,
    "syntaxcheck": 0e0
  },
  "Method::Also": {
    "start": 0e0,
    "ast": 0e0,
    "parse": 1.602e0,
    "mbc": 0.002e0,
    "mast": 0.008e0,
    "syntaxcheck": 0e0,
    "moar": 0e0,
    "optimize": 0.002e0
  },
  "WebkitGTK::Download": {
    "ast": 0e0,
    "start": 0e0,
    "mbc": 0.001e0,
    "parse": 7.627e0,
    "mast": 0.009e0,
    "moar": 0e0,
    "syntaxcheck": 0e0,
    "optimize": 0.002e0
  },
  "WebkitGTK::URIRequest": {
    "ast": 0e0,
    "start": 0e0,
    "mbc": 0.001e0,
    "parse": 3.897e0,
    "mast": 0.01e0,
    "optimize": 0.002e0,
    "moar": 0e0,
    "syntaxcheck": 0e0
  },
  "WebkitGTK::Raw::Credential": {
    "start": 0e0,
    "ast": 0e0,
    "parse": 4.564e0,
    "mbc": 0.002e0,
    "mast": 0.011e0,
    "optimize": 0.002e0,
    "moar": 0e0,
    "syntaxcheck": 0e0
  },
  "WebkitGTK::JavascriptResult": {
    "start": 0e0,
    "ast": 0e0,
    "parse": 4.528e0,
    "mbc": 0.002e0,
    "mast": 0.01e0,
    "moar": 0e0,
    "syntaxcheck": 0e0,
    "optimize": 0.002e0
  },
  "WebkitGTK::ApplicationInfo": {
    "parse": 3.979e0,
    "mbc": 0.002e0,
    "start": 0e0,
    "ast": 0e0,
    "syntaxcheck": 0e0,
    "moar": 0e0,
    "optimize": 0.002e0,
    "mast": 0.011e0
  },
  "WebkitGTK::Raw::WebResource": {
    "ast": 0e0,
    "start": 0e0,
    "mbc": 0.002e0,
    "parse": 4.3e0,
    "mast": 0.009e0,
    "optimize": 0.002e0,
    "moar": 0e0,
    "syntaxcheck": 0e0
  },
  "WebkitGTK::Roles::Signals::WebView": {
    "optimize": 0.002e0,
    "moar": 0e0,
    "syntaxcheck": 0e0,
    "mast": 0.009e0,
    "mbc": 0.001e0,
    "parse": 8.023e0,
    "ast": 0e0,
    "start": 0e0
  },
  "GTK::PrintSettings": {
    "mast": 0.009e0,
    "syntaxcheck": 0e0,
    "moar": 0e0,
    "optimize": 0.002e0,
    "start": 0e0,
    "ast": 0e0,
    "parse": 1.816e0,
    "mbc": 0.001e0
  },
  "WebkitGTK::OptionMenuItem": {
    "optimize": 0.002e0,
    "moar": 0e0,
    "syntaxcheck": 0e0,
    "mast": 0.01e0,
    "parse": 4.179e0,
    "mbc": 0.001e0,
    "start": 0e0,
    "ast": 0e0
  },
  "WebkitGTK::Raw::UserContentManager": {
    "mast": 0.01e0,
    "moar": 0e0,
    "syntaxcheck": 0e0,
    "optimize": 0.005e0,
    "start": 0e0,
    "ast": 0e0,
    "parse": 4.913e0,
    "mbc": 0.002e0
  },
  "WebkitGTK::ResponsePolicyDecision": {
    "mast": 0.01e0,
    "optimize": 0.003e0,
    "moar": 0e0,
    "syntaxcheck": 0e0,
    "start": 0e0,
    "ast": 0e0,
    "parse": 4.558e0,
    "mbc": 0.002e0
  },
  "WebkitGTK::CookieManager": {
    "mast": 0.009e0,
    "moar": 0e0,
    "optimize": 0.002e0,
    "syntaxcheck": 0e0,
    "ast": 0e0,
    "start": 0e0,
    "mbc": 0.001e0,
    "parse": 4.858e0
  },
  "WebkitGTK::Raw::Types": {
    "mast": 0.014e0,
    "optimize": 0.007e0,
    "moar": 0e0,
    "syntaxcheck": 0e0,
    "ast": 0e0,
    "start": 0e0,
    "mbc": 0.007e0,
    "parse": 5.75e0
  },
  "GTK::Raw::Types": {
    "mbc": 0.02e0,
    "parse": 1.751e0,
    "ast": 0e0,
    "start": 0e0,
    "moar": 0e0,
    "optimize": 0.018e0,
    "syntaxcheck": 0e0,
    "mast": 0.036e0
  },
  "WebkitGTK::Raw::ResponsePolicyDecision": {
    "start": 0e0,
    "ast": 0e0,
    "parse": 4.278e0,
    "mbc": 0.001e0,
    "mast": 0.011e0,
    "optimize": 0.002e0,
    "moar": 0e0,
    "syntaxcheck": 0e0
  },
  "tainted": [
    false,
    false,
    false,
    false,
    false,
    false,
    false,
    false,
    false,
    false,
    false,
    false,
    false,
    false,
    false,
    false,
    false,
    false,
    false,
    false,
    false,
    false,
    false,
    false,
    false,
    false,
    false,
    false,
    false,
    false,
    false,
    false,
    false,
    false,
    false,
    false,
    false,
    false,
    false,
    false,
    false,
    false,
    false,
    false,
    false,
    false,
    false,
    false,
    false,
    false,
    false,
    false,
    false,
    false,
    false,
    false,
    false,
    false,
    false,
    false,
    false,
    false,
    false,
    false,
    false,
    false,
    false,
    false,
    false,
    false,
    false,
    false,
    false,
    false,
    false,
    false,
    false,
    false,
    false,
    false,
    false,
    false,
    false,
    false,
    false,
    false,
    false,
    false,
    false,
    false,
    false,
    false,
    false,
    false,
    false,
    false,
    false,
    false,
    false,
    false,
    false,
    false,
    false,
    false,
    false,
    false,
    false,
    false,
    false,
    false,
    false,
    false,
    false,
    false,
    false,
    false,
    false,
    false,
    false,
    false,
    false,
    false,
    false,
    false,
    false,
    false,
    false,
    false,
    false,
    false,
    false,
    false,
    false,
    false,
    false,
    false,
    false,
    false,
    false,
    false
  ],
  "WebkitGTK::Roles::Signals::WebResource": {
    "optimize": 0.002e0,
    "moar": 0e0,
    "syntaxcheck": 0e0,
    "mast": 0.009e0,
    "parse": 4.757e0,
    "mbc": 0.001e0,
    "start": 0e0,
    "ast": 0e0
  },
  "WebkitGTK::Roles::Signals::PrintCustomWidget": {
    "moar": 0e0,
    "syntaxcheck": 0e0,
    "optimize": 0.002e0,
    "mast": 0.01e0,
    "parse": 4.74e0,
    "mbc": 0.001e0,
    "start": 0e0,
    "ast": 0e0
  },
  "WebkitGTK::ConsoleMessage": {
    "mbc": 0.001e0,
    "parse": 4.008e0,
    "ast": 0e0,
    "start": 0e0,
    "syntaxcheck": 0e0,
    "moar": 0e0,
    "optimize": 0.002e0,
    "mast": 0.008e0
  },
  "WebkitGTK::Raw::NavigationAction": {
    "ast": 0e0,
    "start": 0e0,
    "mbc": 0.003e0,
    "parse": 4.753e0,
    "mast": 0.01e0,
    "optimize": 0.003e0,
    "moar": 0e0,
    "syntaxcheck": 0e0
  },
  "WebkitGTK::Raw::WindowProperties": {
    "mbc": 0.002e0,
    "parse": 4.664e0,
    "ast": 0e0,
    "start": 0e0,
    "syntaxcheck": 0e0,
    "moar": 0e0,
    "optimize": 0.002e0,
    "mast": 0.01e0
  },
  "WebkitGTK::WebResource": {
    "syntaxcheck": 0e0,
    "moar": 0e0,
    "optimize": 0.002e0,
    "mast": 0.01e0,
    "mbc": 0.001e0,
    "parse": 4.245e0,
    "ast": 0e0,
    "start": 0e0
  },
  "WebkitGTK::AutomationSession": {
    "mast": 0.009e0,
    "optimize": 0.002e0,
    "moar": 0e0,
    "syntaxcheck": 0e0,
    "start": 0e0,
    "ast": 0e0,
    "parse": 4.114e0,
    "mbc": 0.001e0
  },
  "WebkitGTK::Raw::OptionMenuItem": {
    "mast": 0.009e0,
    "syntaxcheck": 0e0,
    "moar": 0e0,
    "optimize": 0.002e0,
    "start": 0e0,
    "ast": 0e0,
    "parse": 4.596e0,
    "mbc": 0.002e0
  },
  "WebkitGTK::Raw::AuthenticationRequest": {
    "parse": 5.002e0,
    "mbc": 0.002e0,
    "start": 0e0,
    "ast": 0e0,
    "moar": 0e0,
    "syntaxcheck": 0e0,
    "optimize": 0.003e0,
    "mast": 0.011e0
  },
  "WebkitGTK::Raw::SecurityManager": {
    "parse": 5.287e0,
    "mbc": 0.003e0,
    "start": 0e0,
    "ast": 0e0,
    "optimize": 0.003e0,
    "moar": 0e0,
    "syntaxcheck": 0e0,
    "mast": 0.01e0
  },
  "WebkitGTK::Raw::ContextMenu": {
    "start": 0e0,
    "ast": 0e0,
    "parse": 5.574e0,
    "mbc": 0.002e0,
    "mast": 0.01e0,
    "moar": 0e0,
    "optimize": 0.002e0,
    "syntaxcheck": 0e0
  },
  "WebkitGTK::Roles::Signals::AutomationSession": {
    "mbc": 0.001e0,
    "parse": 4.202e0,
    "ast": 0e0,
    "start": 0e0,
    "moar": 0e0,
    "syntaxcheck": 0e0,
    "optimize": 0.002e0,
    "mast": 0.009e0
  },
  "WebkitGTK::Roles::Signals::Download": {
    "start": 0e0,
    "ast": 0e0,
    "parse": 5.052e0,
    "mbc": 0.001e0,
    "mast": 0.01e0,
    "moar": 0e0,
    "optimize": 0.002e0,
    "syntaxcheck": 0e0
  },
  "WebkitGTK::URIResponse": {
    "start": 0e0,
    "ast": 0e0,
    "parse": 5.109e0,
    "mbc": 0.002e0,
    "mast": 0.009e0,
    "optimize": 0.002e0,
    "moar": 0e0,
    "syntaxcheck": 0e0
  },
  "WebkitGTK::Raw::FaviconDatabase": {
    "start": 0e0,
    "ast": 0e0,
    "parse": 4.634e0,
    "mbc": 0.002e0,
    "mast": 0.019e0,
    "moar": 0e0,
    "optimize": 0.003e0,
    "syntaxcheck": 0e0
  },
  "WebkitGTK::PolicyDecision": {
    "start": 0e0,
    "ast": 0e0,
    "parse": 4.261e0,
    "mbc": 0.002e0,
    "mast": 0.01e0,
    "moar": 0e0,
    "optimize": 0.002e0,
    "syntaxcheck": 0e0
  },
  "WebkitGTK::Raw::ContextMenuItem": {
    "optimize": 0.002e0,
    "moar": 0e0,
    "syntaxcheck": 0e0,
    "mast": 0.01e0,
    "parse": 4.897e0,
    "mbc": 0.002e0,
    "start": 0e0,
    "ast": 0e0
  },
  "Cairo": {
    "start": 0e0,
    "ast": 0e0,
    "parse": 1.677e0,
    "mbc": 0.007e0,
    "mast": 0.016e0,
    "moar": 0e0,
    "optimize": 0.007e0,
    "syntaxcheck": 0e0
  },
  "WebkitGTK::Raw::UserContent": {
    "moar": 0e0,
    "syntaxcheck": 0e0,
    "optimize": 0.003e0,
    "mast": 0.011e0,
    "parse": 4.57e0,
    "mbc": 0.002e0,
    "start": 0e0,
    "ast": 0e0
  },
  "WebkitGTK::OptionMenu": {
    "start": 0e0,
    "ast": 0e0,
    "parse": 4.466e0,
    "mbc": 0.001e0,
    "mast": 0.009e0,
    "optimize": 0.002e0,
    "moar": 0e0,
    "syntaxcheck": 0e0
  },
  "WebkitGTK::MimeInfo": {
    "mast": 0.009e0,
    "moar": 0e0,
    "optimize": 0.003e0,
    "syntaxcheck": 0e0,
    "ast": 0e0,
    "start": 0e0,
    "mbc": 0.001e0,
    "parse": 4.077e0
  },
  "WebkitGTK::WebInspector": {
    "moar": 0e0,
    "optimize": 0.002e0,
    "syntaxcheck": 0e0,
    "mast": 0.008e0,
    "mbc": 0.001e0,
    "parse": 4.082e0,
    "ast": 0e0,
    "start": 0e0
  },
  "WebkitGTK::Raw::CookieManager": {
    "mast": 0.011e0,
    "syntaxcheck": 0e0,
    "moar": 0e0,
    "optimize": 0.002e0,
    "start": 0e0,
    "ast": 0e0,
    "parse": 5.039e0,
    "mbc": 0.002e0
  },
  "WebkitGTK::Raw::ColorChooserRequest": {
    "parse": 4.726e0,
    "mbc": 0.001e0,
    "start": 0e0,
    "ast": 0e0,
    "syntaxcheck": 0e0,
    "moar": 0e0,
    "optimize": 0.002e0,
    "mast": 0.01e0
  },
  "WebkitGTK::JavaScript::Raw::Types": {
    "start": 0e0,
    "ast": 0e0,
    "parse": 4.425e0,
    "mbc": 0.002e0,
    "mast": 0.01e0,
    "moar": 0e0,
    "optimize": 0.002e0,
    "syntaxcheck": 0e0
  },
  "GTK::Roles::Signals::Generic": {
    "mbc": 0.002e0,
    "parse": 1.763e0,
    "ast": 0e0,
    "start": 0e0,
    "optimize": 0.002e0,
    "moar": 0e0,
    "syntaxcheck": 0e0,
    "mast": 0.009e0
  },
  "WebkitGTK::Raw::WebContext": {
    "parse": 7.328e0,
    "mbc": 0.003e0,
    "start": 0e0,
    "ast": 0e0,
    "moar": 0e0,
    "optimize": 0.003e0,
    "syntaxcheck": 0e0,
    "mast": 0.011e0
  },
  "WebkitGTK::Raw::Plugin": {
    "ast": 0e0,
    "start": 0e0,
    "mbc": 0.002e0,
    "parse": 4.138e0,
    "mast": 0.012e0,
    "moar": 0e0,
    "syntaxcheck": 0e0,
    "optimize": 0.002e0
  },
  "WebkitGTK::JavaScript::Exception": {
    "mbc": 0.001e0,
    "parse": 4.57e0,
    "ast": 0e0,
    "start": 0e0,
    "moar": 0e0,
    "optimize": 0.003e0,
    "syntaxcheck": 0e0,
    "mast": 0.01e0
  },
  "GTK::Raw::ReturnedValue": {
    "parse": 2.063e0,
    "mbc": 0.001e0,
    "start": 0e0,
    "ast": 0e0,
    "moar": 0e0,
    "syntaxcheck": 0e0,
    "optimize": 0.002e0,
    "mast": 0.018e0
  },
  "WebkitGTK::EditorState": {
    "ast": 0e0,
    "start": 0e0,
    "mbc": 0.001e0,
    "parse": 3.973e0,
    "mast": 0.01e0,
    "moar": 0e0,
    "syntaxcheck": 0e0,
    "optimize": 0.002e0
  },
  "GTK::Compat::Types": {
    "ast": 0e0,
    "start": 0e0,
    "mbc": 0.018e0,
    "parse": 1.696e0,
    "mast": 0.028e0,
    "moar": 0e0,
    "syntaxcheck": 0e0,
    "optimize": 0.017e0
  },
  "WebkitGTK::WebView": {
    "start": 0e0,
    "ast": 0e0,
    "parse": 8.367e0,
    "mbc": 0.001e0,
    "mast": 0.009e0,
    "moar": 0e0,
    "syntaxcheck": 0e0,
    "optimize": 0.002e0
  },
  "GTK::Container": {
    "optimize": 0.003e0,
    "moar": 0e0,
    "syntaxcheck": 0e0,
    "mast": 0.009e0,
    "parse": 2.716e0,
    "mbc": 0.002e0,
    "start": 0e0,
    "ast": 0e0
  },
  "WebkitGTK::FaviconDatabase": {
    "mast": 0.01e0,
    "optimize": 0.002e0,
    "moar": 0e0,
    "syntaxcheck": 0e0,
    "ast": 0e0,
    "start": 0e0,
    "mbc": 0.001e0,
    "parse": 4.483e0
  },
  "WebkitGTK::Raw::PrintOperation": {
    "ast": 0e0,
    "start": 0e0,
    "mbc": 0.002e0,
    "parse": 5.084e0,
    "mast": 0.009e0,
    "syntaxcheck": 0e0,
    "moar": 0e0,
    "optimize": 0.002e0
  },
  "WebkitGTK::SecurityManager": {
    "mast": 0.01e0,
    "moar": 0e0,
    "optimize": 0.002e0,
    "syntaxcheck": 0e0,
    "ast": 0e0,
    "start": 0e0,
    "mbc": 0.001e0,
    "parse": 4.031e0
  },
  "WebkitGTK::Credential": {
    "mbc": 0.002e0,
    "parse": 4.355e0,
    "ast": 0e0,
    "start": 0e0,
    "moar": 0e0,
    "syntaxcheck": 0e0,
    "optimize": 0.002e0,
    "mast": 0.008e0
  },
  "WebkitGTK::HitTestResult": {
    "mbc": 0.001e0,
    "parse": 4.935e0,
    "ast": 0e0,
    "start": 0e0,
    "syntaxcheck": 0e0,
    "moar": 0e0,
    "optimize": 0.002e0,
    "mast": 0.009e0
  },
  "WebkitGTK::Raw::JavascriptResult": {
    "start": 0e0,
    "ast": 0e0,
    "parse": 4.38e0,
    "mbc": 0.002e0,
    "mast": 0.011e0,
    "optimize": 0.002e0,
    "moar": 0e0,
    "syntaxcheck": 0e0
  },
  "WebkitGTK::Raw::FileChooserRequest": {
    "syntaxcheck": 0e0,
    "moar": 0e0,
    "optimize": 0.002e0,
    "mast": 0.008e0,
    "mbc": 0.002e0,
    "parse": 4.699e0,
    "ast": 0e0,
    "start": 0e0
  },
  "WebkitGTK::Raw::Download": {
    "moar": 0e0,
    "syntaxcheck": 0e0,
    "optimize": 0.003e0,
    "mast": 0.012e0,
    "parse": 5.32e0,
    "mbc": 0.002e0,
    "start": 0e0,
    "ast": 0e0
  },
  "WebkitGTK::Compat::Types": {
    "optimize": 0.002e0,
    "moar": 0e0,
    "syntaxcheck": 0e0,
    "mast": 0.009e0,
    "mbc": 0.001e0,
    "parse": 3.529e0,
    "ast": 0e0,
    "start": 0e0
  },
  "GTK::Compat::Roles::Action": {
    "mast": 0.008e0,
    "syntaxcheck": 0e0,
    "moar": 0e0,
    "optimize": 0.002e0,
    "ast": 0e0,
    "start": 0e0,
    "mbc": 0.001e0,
    "parse": 1.83e0
  },
  "WebkitGTK::Roles::Signals::PrintOperation": {
    "mast": 0.009e0,
    "moar": 0e0,
    "syntaxcheck": 0e0,
    "optimize": 0.002e0,
    "ast": 0e0,
    "start": 0e0,
    "mbc": 0.001e0,
    "parse": 4.751e0
  },
  "WebkitGTK::Error": {
    "moar": 0e0,
    "optimize": 0.002e0,
    "syntaxcheck": 0e0,
    "mast": 0.01e0,
    "parse": 3.876e0,
    "mbc": 0.001e0,
    "start": 0e0,
    "ast": 0e0
  },
  "SUMMARY": {
    "real": 636.25e0,
    "user": 751.04e0,
    "sys": 84.9e0
  },
  "WebkitGTK::FileChooserRequest": {
    "mast": 0.009e0,
    "syntaxcheck": 0e0,
    "moar": 0e0,
    "optimize": 0.002e0,
    "start": 0e0,
    "ast": 0e0,
    "parse": 4.554e0,
    "mbc": 0.001e0
  },
  "WebkitGTK::Raw::ApplicationInfo": {
    "syntaxcheck": 0e0,
    "moar": 0e0,
    "optimize": 0.002e0,
    "mast": 0.01e0,
    "parse": 4.927e0,
    "mbc": 0.002e0,
    "start": 0e0,
    "ast": 0e0
  },
  "GTK::Roles::Pointers": {
    "ast": 0e0,
    "start": 0e0,
    "mbc": 0.001e0,
    "parse": 1.637e0,
    "mast": 0.009e0,
    "moar": 0e0,
    "syntaxcheck": 0e0,
    "optimize": 0.002e0
  },
  "WebkitGTK::SecurityOrigin": {
    "moar": 0e0,
    "syntaxcheck": 0e0,
    "optimize": 0.003e0,
    "mast": 0.009e0,
    "mbc": 0.001e0,
    "parse": 4.238e0,
    "ast": 0e0,
    "start": 0e0
  },
  "WebkitGTK::Settings": {
    "moar": 0e0,
    "optimize": 0.002e0,
    "syntaxcheck": 0e0,
    "mast": 0.012e0,
    "parse": 5.381e0,
    "mbc": 0.001e0,
    "start": 0e0,
    "ast": 0e0
  },
  "WebkitGTK::AuthenticationRequest": {
    "mast": 0.009e0,
    "moar": 0e0,
    "optimize": 0.002e0,
    "syntaxcheck": 0e0,
    "start": 0e0,
    "ast": 0e0,
    "parse": 4.509e0,
    "mbc": 0.001e0
  },
  "WebkitGTK::JavaScript::Context": {
    "mast": 0.01e0,
    "moar": 0e0,
    "syntaxcheck": 0e0,
    "optimize": 0.004e0,
    "ast": 0e0,
    "start": 0e0,
    "mbc": 0.002e0,
    "parse": 5.063e0
  },
  "WebkitGTK::Raw::Error": {
    "syntaxcheck": 0e0,
    "moar": 0e0,
    "optimize": 0.002e0,
    "mast": 0.011e0,
    "mbc": 0.002e0,
    "parse": 4.51e0,
    "ast": 0e0,
    "start": 0e0
  },
  "WebkitGTK::JavaScript::Raw::Class": {
    "parse": 4.535e0,
    "mbc": 0.001e0,
    "start": 0e0,
    "ast": 0e0,
    "optimize": 0.002e0,
    "moar": 0e0,
    "syntaxcheck": 0e0,
    "mast": 0.008e0
  },
  "WebkitGTK::JavaScript::Raw::Exception": {
    "ast": 0e0,
    "start": 0e0,
    "mbc": 0.003e0,
    "parse": 5.155e0,
    "mast": 0.011e0,
    "optimize": 0.002e0,
    "moar": 0e0,
    "syntaxcheck": 0e0
  },
  "GTK::FileFilter": {
    "mast": 0.009e0,
    "syntaxcheck": 0e0,
    "moar": 0e0,
    "optimize": 0.002e0,
    "start": 0e0,
    "ast": 0e0,
    "parse": 1.826e0,
    "mbc": 0.001e0
  },
  "WebkitGTK::Raw::WebInspector": {
    "parse": 4.687e0,
    "mbc": 0.001e0,
    "start": 0e0,
    "ast": 0e0,
    "moar": 0e0,
    "syntaxcheck": 0e0,
    "optimize": 0.003e0,
    "mast": 0.01e0
  },
  "WebkitGTK::JavaScript::Raw::VM": {
    "syntaxcheck": 0e0,
    "moar": 0e0,
    "optimize": 0.002e0,
    "mast": 0.009e0,
    "parse": 3.583e0,
    "mbc": 0.002e0,
    "start": 0e0,
    "ast": 0e0
  },
  "WebkitGTK::JavaScript::Utils": {
    "start": 0e0,
    "ast": 0e0,
    "parse": 3.551e0,
    "mbc": 0.001e0,
    "mast": 0.009e0,
    "optimize": 0.002e0,
    "moar": 0e0,
    "syntaxcheck": 0e0
  },
  "GTK::Roles::Types": {
    "mast": 0.01e0,
    "moar": 0e0,
    "syntaxcheck": 0e0,
    "optimize": 0.002e0,
    "start": 0e0,
    "ast": 0e0,
    "parse": 1.646e0,
    "mbc": 0.001e0
  },
  "WebkitGTK::Raw::Frame": {
    "ast": 0e0,
    "start": 0e0,
    "mbc": 0.002e0,
    "parse": 4.241e0,
    "mast": 0.011e0,
    "moar": 0e0,
    "syntaxcheck": 0e0,
    "optimize": 0.002e0
  },
  "WebkitGTK::Raw::PolicyDecision": {
    "moar": 0e0,
    "optimize": 0.004e0,
    "syntaxcheck": 0e0,
    "mast": 0.008e0,
    "mbc": 0.003e0,
    "parse": 3.982e0,
    "ast": 0e0,
    "start": 0e0
  },
  "WebkitGTK::Raw::Notification": {
    "optimize": 0.002e0,
    "moar": 0e0,
    "syntaxcheck": 0e0,
    "mast": 0.012e0,
    "mbc": 0.002e0,
    "parse": 5.021e0,
    "ast": 0e0,
    "start": 0e0
  },
  "WebkitGTK::URISchemeRequest": {
    "mast": 0.012e0,
    "syntaxcheck": 0e0,
    "moar": 0e0,
    "optimize": 0.004e0,
    "ast": 0e0,
    "start": 0e0,
    "mbc": 0.001e0,
    "parse": 4.204e0
  },
  "WebkitGTK::PrintOperation": {
    "syntaxcheck": 0e0,
    "moar": 0e0,
    "optimize": 0.005e0,
    "mast": 0.009e0,
    "parse": 4.839e0,
    "mbc": 0.002e0,
    "start": 0e0,
    "ast": 0e0
  },
  "WebkitGTK::Roles::PermissionRequest": {
    "syntaxcheck": 0e0,
    "moar": 0e0,
    "optimize": 0.002e0,
    "mast": 0.009e0,
    "mbc": 0.002e0,
    "parse": 3.911e0,
    "ast": 0e0,
    "start": 0e0
  },
  "WebkitGTK::NavigationAction": {
    "ast": 0e0,
    "start": 0e0,
    "mbc": 0.002e0,
    "parse": 4.16e0,
    "mast": 0.01e0,
    "moar": 0e0,
    "syntaxcheck": 0e0,
    "optimize": 0.002e0
  },
  "WebkitGTK::Version": {
    "start": 0e0,
    "ast": 0e0,
    "parse": 4.016e0,
    "mbc": 0.001e0,
    "mast": 0.01e0,
    "optimize": 0.002e0,
    "moar": 0e0,
    "syntaxcheck": 0e0
  },
  "WebkitGTK::UserContent": {
    "mast": 0.009e0,
    "moar": 0e0,
    "optimize": 0.004e0,
    "syntaxcheck": 0e0,
    "ast": 0e0,
    "start": 0e0,
    "mbc": 0.001e0,
    "parse": 4.874e0
  },
  "WebkitGTK::Raw::URISchemeRequest": {
    "parse": 4.363e0,
    "mbc": 0.002e0,
    "start": 0e0,
    "ast": 0e0,
    "moar": 0e0,
    "optimize": 0.002e0,
    "syntaxcheck": 0e0,
    "mast": 0.012e0
  },
  "WebkitGTK::Roles::Signals::UserContentManager": {
    "start": 0e0,
    "ast": 0e0,
    "parse": 3.986e0,
    "mbc": 0.002e0,
    "mast": 0.009e0,
    "optimize": 0.002e0,
    "moar": 0e0,
    "syntaxcheck": 0e0
  },
  "WebkitGTK::Raw::NetworkProxySettings": {
    "mast": 0.01e0,
    "moar": 0e0,
    "syntaxcheck": 0e0,
    "optimize": 0.002e0,
    "start": 0e0,
    "ast": 0e0,
    "parse": 4.431e0,
    "mbc": 0.001e0
  },
  "WebkitGTK::WebContext": {
    "mbc": 0.002e0,
    "parse": 4.867e0,
    "ast": 0e0,
    "start": 0e0,
    "moar": 0e0,
    "optimize": 0.003e0,
    "syntaxcheck": 0e0,
    "mast": 0.01e0
  },
  "WebkitGTK::ColorChooserRequest": {
    "ast": 0e0,
    "start": 0e0,
    "mbc": 0.001e0,
    "parse": 4.34e0,
    "mast": 0.01e0,
    "moar": 0e0,
    "optimize": 0.002e0,
    "syntaxcheck": 0e0
  },
  "WebkitGTK::Raw::BackForwardListItem": {
    "mast": 0.01e0,
    "moar": 0e0,
    "syntaxcheck": 0e0,
    "optimize": 0.002e0,
    "ast": 0e0,
    "start": 0e0,
    "mbc": 0.001e0,
    "parse": 4.358e0
  },
  "WebkitGTK::Raw::MimeInfo": {
    "start": 0e0,
    "ast": 0e0,
    "parse": 4.61e0,
    "mbc": 0.002e0,
    "mast": 0.011e0,
    "moar": 0e0,
    "optimize": 0.002e0,
    "syntaxcheck": 0e0
  },
  "WebkitGTK::WebsiteDataManager": {
    "mbc": 0.001e0,
    "parse": 5.303e0,
    "ast": 0e0,
    "start": 0e0,
    "optimize": 0.002e0,
    "moar": 0e0,
    "syntaxcheck": 0e0,
    "mast": 0.009e0
  },
  "DEPENDENCIES": {
    "real": 2.97e0,
    "user": 3.32e0,
    "sys": 0.49e0
  },
  "WebkitGTK::Raw::AutomationSession": {
    "mbc": 0.002e0,
    "parse": 4.022e0,
    "ast": 0e0,
    "start": 0e0,
    "syntaxcheck": 0e0,
    "moar": 0e0,
    "optimize": 0.002e0,
    "mast": 0.008e0
  },
  "WebkitGTK::Raw::FindController": {
    "moar": 0e0,
    "syntaxcheck": 0e0,
    "optimize": 0.002e0,
    "mast": 0.013e0,
    "mbc": 0.002e0,
    "parse": 4.695e0,
    "ast": 0e0,
    "start": 0e0
  },
  "WebkitGTK::Raw::NativgationPolicyDecision": {
    "optimize": 0.002e0,
    "moar": 0e0,
    "syntaxcheck": 0e0,
    "mast": 0.01e0,
    "mbc": 0.002e0,
    "parse": 4.376e0,
    "ast": 0e0,
    "start": 0e0
  },
  "WebkitGTK::JavaScript::Raw::Context": {
    "ast": 0e0,
    "start": 0e0,
    "mbc": 0.002e0,
    "parse": 5.65e0,
    "mast": 0.01e0,
    "optimize": 0.002e0,
    "moar": 0e0,
    "syntaxcheck": 0e0
  },
  "WebkitGTK::ContextMenu": {
    "optimize": 0.006e0,
    "moar": 0e0,
    "syntaxcheck": 0e0,
    "mast": 0.011e0,
    "mbc": 0.001e0,
    "parse": 4.352e0,
    "ast": 0e0,
    "start": 0e0
  },
  "WebkitGTK::UserContentManager": {
    "ast": 0e0,
    "start": 0e0,
    "mbc": 0.001e0,
    "parse": 4.148e0,
    "mast": 0.01e0,
    "optimize": 0.002e0,
    "moar": 0e0,
    "syntaxcheck": 0e0
  },
  "WebkitGTK::Plugin": {
    "start": 0e0,
    "ast": 0e0,
    "parse": 4.501e0,
    "mbc": 0.002e0,
    "mast": 0.009e0,
    "optimize": 0.002e0,
    "moar": 0e0,
    "syntaxcheck": 0e0
  },
  "WebkitGTK::NavigationPolicyDecision": {
    "mbc": 0.001e0,
    "parse": 4.454e0,
    "ast": 0e0,
    "start": 0e0,
    "moar": 0e0,
    "syntaxcheck": 0e0,
    "optimize": 0.002e0,
    "mast": 0.009e0
  },
  "WebkitGTK::FormSubmissionRequest": {
    "mast": 0.01e0,
    "moar": 0e0,
    "syntaxcheck": 0e0,
    "optimize": 0.002e0,
    "ast": 0e0,
    "start": 0e0,
    "mbc": 0.002e0,
    "parse": 4.172e0
  },
  "GTK::Compat::RGBA": {
    "moar": 0e0,
    "syntaxcheck": 0e0,
    "optimize": 0.002e0,
    "mast": 0.01e0,
    "mbc": 0.002e0,
    "parse": 1.693e0,
    "ast": 0e0,
    "start": 0e0
  },
  "WebkitGTK::Raw::PermissionRequest": {
    "optimize": 0.002e0,
    "moar": 0e0,
    "syntaxcheck": 0e0,
    "mast": 0.01e0,
    "mbc": 0.001e0,
    "parse": 4.544e0,
    "ast": 0e0,
    "start": 0e0
  },
  "WebkitGTK::Raw::OptionMenu": {
    "mast": 0.02e0,
    "optimize": 0.002e0,
    "moar": 0e0,
    "syntaxcheck": 0e0,
    "start": 0e0,
    "ast": 0e0,
    "parse": 4.351e0,
    "mbc": 0.001e0
  },
  "WebkitGTK::Raw::URIRequest": {
    "mast": 0.011e0,
    "moar": 0e0,
    "optimize": 0.002e0,
    "syntaxcheck": 0e0,
    "start": 0e0,
    "ast": 0e0,
    "parse": 4.362e0,
    "mbc": 0.002e0
  },
  "WebkitGTK::Raw::Version": {
    "moar": 0e0,
    "optimize": 0.003e0,
    "syntaxcheck": 0e0,
    "mast": 0.015e0,
    "parse": 4.352e0,
    "mbc": 0.002e0,
    "start": 0e0,
    "ast": 0e0
  },
  "WebkitGTK::WindowProperties": {
    "start": 0e0,
    "ast": 0e0,
    "parse": 4.8e0,
    "mbc": 0.001e0,
    "mast": 0.009e0,
    "moar": 0e0,
    "optimize": 0.002e0,
    "syntaxcheck": 0e0
  },
  "WebkitGTK::JavaScript::Raw::Value": {
    "mbc": 0.003e0,
    "parse": 7.655e0,
    "ast": 0e0,
    "start": 0e0,
    "moar": 0e0,
    "optimize": 0.003e0,
    "syntaxcheck": 0e0,
    "mast": 0.011e0
  },
  "GTK::Compat::Roles::Object": {
    "mast": 0.009e0,
    "moar": 0e0,
    "syntaxcheck": 0e0,
    "optimize": 0.002e0,
    "ast": 0e0,
    "start": 0e0,
    "mbc": 0.002e0,
    "parse": 1.744e0
  },
  "WebkitGTK::JavaScript::Value": {
    "optimize": 0.002e0,
    "moar": 0e0,
    "syntaxcheck": 0e0,
    "mast": 0.009e0,
    "parse": 4.818e0,
    "mbc": 0.002e0,
    "start": 0e0,
    "ast": 0e0
  },
  "WebkitGTK::WebsiteData": {
    "start": 0e0,
    "ast": 0e0,
    "parse": 4.433e0,
    "mbc": 0.002e0,
    "mast": 0.01e0,
    "optimize": 0.003e0,
    "moar": 0e0,
    "syntaxcheck": 0e0
  },
  "WebkitGTK::Raw::BackForwardList": {
    "ast": 0e0,
    "start": 0e0,
    "mbc": 0.002e0,
    "parse": 4.69e0,
    "mast": 0.012e0,
    "moar": 0e0,
    "optimize": 0.002e0,
    "syntaxcheck": 0e0
  },
  "WebkitGTK::Raw::PrintCustomWidget": {
    "start": 0e0,
    "ast": 0e0,
    "parse": 4.682e0,
    "mbc": 0.001e0,
    "mast": 0.01e0,
    "syntaxcheck": 0e0,
    "moar": 0e0,
    "optimize": 0.002e0
  },
  "WebkitGTK::Raw::WebsiteData": {
    "moar": 0e0,
    "syntaxcheck": 0e0,
    "optimize": 0.002e0,
    "mast": 0.011e0,
    "mbc": 0.002e0,
    "parse": 4.295e0,
    "ast": 0e0,
    "start": 0e0
  },
  "WebkitGTK::Frame": {
    "mast": 0.01e0,
    "syntaxcheck": 0e0,
    "moar": 0e0,
    "optimize": 0.002e0,
    "start": 0e0,
    "ast": 0e0,
    "parse": 3.867e0,
    "mbc": 0.001e0
  },
  "WebkitGTK::JavaScript::VM": {
    "syntaxcheck": 0e0,
    "moar": 0e0,
    "optimize": 0.002e0,
    "mast": 0.009e0,
    "mbc": 0.001e0,
    "parse": 3.507e0,
    "ast": 0e0,
    "start": 0e0
  },
  "GTK::Raw::Utils": {
    "mast": 0.01e0,
    "syntaxcheck": 0e0,
    "moar": 0e0,
    "optimize": 0.002e0,
    "ast": 0e0,
    "start": 0e0,
    "mbc": 0.002e0,
    "parse": 1.558e0
  },
  "GTK::PageSetup": {
    "parse": 1.837e0,
    "mbc": 0.001e0,
    "start": 0e0,
    "ast": 0e0,
    "optimize": 0.002e0,
    "moar": 0e0,
    "syntaxcheck": 0e0,
    "mast": 0.008e0
  },
  "WebkitGTK::Raw::WebsiteDataManager": {
    "optimize": 0.002e0,
    "moar": 0e0,
    "syntaxcheck": 0e0,
    "mast": 0.01e0,
    "mbc": 0.002e0,
    "parse": 5.422e0,
    "ast": 0e0,
    "start": 0e0
  },
  "WebkitGTK::Raw::NavigationPolicyDecision": {
    "mbc": 0.001e0,
    "parse": 3.976e0,
    "ast": 0e0,
    "start": 0e0,
    "moar": 0e0,
    "optimize": 0.002e0,
    "syntaxcheck": 0e0,
    "mast": 0.008e0
  },
  "WebkitGTK::Raw::FormSubmissionRequest": {
    "ast": 0e0,
    "start": 0e0,
    "mbc": 0.001e0,
    "parse": 4.601e0,
    "mast": 0.009e0,
    "syntaxcheck": 0e0,
    "moar": 0e0,
    "optimize": 0.002e0
  },
  "WebkitGTK::Notification": {
    "mast": 0.01e0,
    "optimize": 0.002e0,
    "moar": 0e0,
    "syntaxcheck": 0e0,
    "start": 0e0,
    "ast": 0e0,
    "parse": 4.721e0,
    "mbc": 0.002e0
  },
  "WebkitGTK::FindController": {
    "mbc": 0.001e0,
    "parse": 4.71e0,
    "ast": 0e0,
    "start": 0e0,
    "syntaxcheck": 0e0,
    "moar": 0e0,
    "optimize": 0.002e0,
    "mast": 0.01e0
  },
  "WebkitGTK::Raw::HitTestResult": {
    "mast": 0.009e0,
    "moar": 0e0,
    "syntaxcheck": 0e0,
    "optimize": 0.003e0,
    "start": 0e0,
    "ast": 0e0,
    "parse": 4.891e0,
    "mbc": 0.002e0
  },
  "WebkitGTK::Raw::Settings": {
    "mast": 0.012e0,
    "moar": 0e0,
    "syntaxcheck": 0e0,
    "optimize": 0.004e0,
    "ast": 0e0,
    "start": 0e0,
    "mbc": 0.005e0,
    "parse": 13.005e0
  }
}
